otonagai_dl/main.py
otonagai_dl/src/__init__.py
otonagai_dl/src/controller.py
otonagai_dl/src/hobby_link_jp_scraper/__init__.py
otonagai_dl/src/hobby_link_jp_scraper/hlj_batch.py
otonagai_dl/src/hobby_link_jp_scraper/hlj_dl.py
otonagai_dl/src/hobby_link_jp_scraper/hlj_ui.py
otonagai_dl/src/log_system.py
otonagai_dl/src/menu.py
otonagai_dl/src/model.py
otonagai_dl/src/utils.py
otonagai_dl/src/view.py
otonagai_dl/src/warning_shots.py
otonagai_dl-1.0.8.dist-info/entry_points.txt
otonagai_dl-1.0.8.dist-info/LICENSE
otonagai_dl-1.0.8.dist-info/METADATA
otonagai_dl-1.0.8.dist-info/WHEEL
otonagai_dl-1.0.8.dist-info/RECORD
