Metadata-Version: 2.1
Name: otonagai-dl
Version: 1.0.8
Summary: A basic CLI tool to keep track of your favourite anime/manga/comics/pop culture merchandise
License: MIT
Author: Clavin Dsouza
Author-email: clavind12@gmail.com
Requires-Python: >=3.10,<4.0
Classifier: License :: OSI Approved :: MIT License
Classifier: Programming Language :: Python :: 3
Classifier: Programming Language :: Python :: 3.10
Classifier: Programming Language :: Python :: 3.11
Classifier: Programming Language :: Python :: 3.12
Requires-Dist: beautifulsoup4 (>=4.12.3,<5.0.0)
Requires-Dist: inquirerpy (==0.3.4)
Requires-Dist: readchar
Requires-Dist: requests (>=2.31.0,<3.0.0)
Requires-Dist: rich (>=13.7.1,<14.0.0)
